pycord/multicog/__init__.py
pycord_multicog-2.1.1.dist-info/LICENSE.txt
pycord_multicog-2.1.1.dist-info/METADATA
pycord_multicog-2.1.1.dist-info/WHEEL
pycord_multicog-2.1.1.dist-info/top_level.txt
pycord_multicog-2.1.1.dist-info/RECORD
