Metadata-Version: 2.1
Name: pycord-multicog
Version: 2.1.1
Summary: A pycord extension that allows splitting command groups into multiple cogs
Home-page: https://github.com/Dorukyum/pycord-multicog
Author: Dorukyum
License: MIT
Project-URL: Source, https://github.com/Dorukyum/pycord-multicog
Keywords: Pycord
Classifier: License :: OSI Approved :: MIT License
Classifier: Programming Language :: Python :: 3
License-File: LICENSE.txt
Requires-Dist: py-cord >=2.5.0
